douyin_uid_package/__init__.py
douyin_uid_package/douyin_uid_pypi.py
douyin_uid_package-0.0.2.dist-info/METADATA
douyin_uid_package-0.0.2.dist-info/WHEEL
douyin_uid_package-0.0.2.dist-info/top_level.txt
douyin_uid_package-0.0.2.dist-info/RECORD
