Metadata-Version: 2.1
Name: douyin-uid-package
Version: 0.0.2
Summary: A library for obtaining tiktok uid
Home-page: https://github.com/qjga5012/douyin_uid_package
Author: caohui524
Author-email: 408141249@qq.com
License: MIT
Platform: UNKNOWN
Classifier: Development Status :: 3 - Alpha
Classifier: Intended Audience :: Developers
Classifier: License :: OSI Approved :: MIT License
Classifier: Programming Language :: Python :: 3
Classifier: Programming Language :: Python :: 3.6
Classifier: Programming Language :: Python :: 3.7
Classifier: Programming Language :: Python :: 3.8
Classifier: Programming Language :: Python :: 3.9
Requires-Dist: requests
